base/__init__.py
base/memoria.py
gerador/__init__.py
gerador/palavra.py
gerapalavras-0.0.1.dist-info/LICENSE
gerapalavras-0.0.1.dist-info/METADATA
gerapalavras-0.0.1.dist-info/WHEEL
gerapalavras-0.0.1.dist-info/top_level.txt
gerapalavras-0.0.1.dist-info/RECORD
